SBG_TIR_exit_codes/SBG_TIR_exit_codes.py
SBG_TIR_exit_codes/__init__.py
SBG_TIR_exit_codes/version.txt
sbg_tir_exit_codes-1.0.1.dist-info/licenses/LICENSE
sbg_tir_exit_codes-1.0.1.dist-info/METADATA
sbg_tir_exit_codes-1.0.1.dist-info/WHEEL
sbg_tir_exit_codes-1.0.1.dist-info/top_level.txt
sbg_tir_exit_codes-1.0.1.dist-info/RECORD
